MANIFEST.in
setup.py
djangocms_revolutionslider.egg-info/PKG-INFO
djangocms_revolutionslider.egg-info/SOURCES.txt
djangocms_revolutionslider.egg-info/dependency_links.txt
djangocms_revolutionslider.egg-info/top_level.txt
revolutionslider/.DS_Store
revolutionslider/__init__.py
revolutionslider/admin.py
revolutionslider/cms_plugins.py
revolutionslider/models.py
revolutionslider/tests.py
revolutionslider/views.py
revolutionslider/migrations/0001_initial.py
revolutionslider/migrations/0002_auto_20150918_1631.py
revolutionslider/migrations/0003_auto_20150921_1647.py
revolutionslider/migrations/0004_auto_20150921_2055.py
revolutionslider/migrations/0005_auto_20150922_1135.py
revolutionslider/migrations/0006_auto_20150922_1152.py
revolutionslider/migrations/0007_auto_20150923_1738.py
revolutionslider/migrations/0008_auto_20150928_1142.py
revolutionslider/migrations/__init__.py
revolutionslider/south_migrations/0001_initial.py
revolutionslider/south_migrations/__init__.py
revolutionslider/static/vendor/rs-plugin/assets/arrow_large_left.png
revolutionslider/static/vendor/rs-plugin/assets/arrow_large_right.png
revolutionslider/static/vendor/rs-plugin/assets/arrow_left.png
revolutionslider/static/vendor/rs-plugin/assets/arrow_left2.png
revolutionslider/static/vendor/rs-plugin/assets/arrow_right.png
revolutionslider/static/vendor/rs-plugin/assets/arrow_right2.png
revolutionslider/static/vendor/rs-plugin/assets/arrowleft.png
revolutionslider/static/vendor/rs-plugin/assets/arrowright.png
revolutionslider/static/vendor/rs-plugin/assets/arrows.psd
revolutionslider/static/vendor/rs-plugin/assets/black50.png
revolutionslider/static/vendor/rs-plugin/assets/boxed_bgtile.png
revolutionslider/static/vendor/rs-plugin/assets/bullet.png
revolutionslider/static/vendor/rs-plugin/assets/bullet_boxed.png
revolutionslider/static/vendor/rs-plugin/assets/bullets.png
revolutionslider/static/vendor/rs-plugin/assets/bullets.psd
revolutionslider/static/vendor/rs-plugin/assets/bullets2.png
revolutionslider/static/vendor/rs-plugin/assets/coloredbg.png
revolutionslider/static/vendor/rs-plugin/assets/grain.png
revolutionslider/static/vendor/rs-plugin/assets/gridtile.png
