Metadata-Version: 1.1
Name: djangocms-revolutionslider
Version: 0.9
Summary: Quick and easy Implementation of revolution slider
Home-page: https://github.com/royendgel
Author: Royendgel Silberie
Author-email: royendgel@techprocur.com
License: UNKNOWN
Keywords: revolution slider,django,django-cms
Platform: UNKNOWN
Classifier: Operating System :: MacOS :: MacOS X
Classifier: Operating System :: Unix
Classifier: Development Status :: 3 - Alpha
Classifier: Topic :: Utilities
Classifier: Programming Language :: Python :: 2.7
Classifier: Programming Language :: Python :: 3
